<vector android:height="24dp" android:viewportHeight="580"
    android:viewportWidth="580" android:width="24dp" xmlns:android="http://schemas.android.com/apk/res/android">
    <group>
        <clip-path android:pathData="M0,0H580V580H0V0Z M 0,0"/>
        <path android:fillColor="#00000000"
            android:pathData="M66.275 1.76815C24.94 1.76815 1.70398 23.1391 1.70398 66.8041V516.927C1.70398 557.771 22.598 579.156 63.896 579.156H515.92C557.227 579.156 578.149 558.84 578.149 516.927V66.8041C578.149 24.2031 557.227 1.76815 514.627 1.76815C514.624 1.76815 66.133 1.62515 66.275 1.76815Z"
            android:strokeColor="#EEEEEE" android:strokeWidth="3.408"/>
        <path android:fillColor="#ff8f00" android:fillType="evenOdd" android:pathData="M210.586 66.7812C197.327 67.3748 182.795 79.1973 169.83 79.9062C169.595 79.9105 169.36 79.9093 169.125 79.9062V111.187C169.36 111.19 169.595 111.223 169.83 111.219C182.795 110.63 197.327 98.5077 210.586 98.0937C223.502 97.504 235.044 108.483 248.059 108.719C261.269 108.839 274.671 98.7988 288.814 99.0937C302.761 99.3283 316.957 110.275 331.198 110.219C345.193 109.864 358.454 98.2116 373.039 98.0937C383.813 98.0521 395.391 104.219 406.469 107.594V76.2187C395.391 72.8684 383.813 66.7812 373.039 66.7812C358.454 66.9004 345.193 78.5511 331.198 78.9062C316.957 78.9639 302.761 68.0483 288.814 67.8124C274.671 67.3996 261.269 77.4954 248.059 77.3749C235.045 77.0814 223.502 66.3094 210.586 66.7812V66.7812Z"/>
        <path android:fillColor="#ff8f00" android:fillType="evenOdd" android:pathData="M211.807 125.156C211.406 125.15 210.99 125.173 210.586 125.187C197.327 125.777 182.795 137.57 169.83 138.281C169.595 138.285 169.36 138.284 169.125 138.281V169.594C169.36 169.597 169.595 169.598 169.83 169.594C182.795 168.882 197.327 157.058 210.586 156.469C223.502 155.996 235.044 166.768 248.059 167.062C261.269 167.18 274.671 157.086 288.814 157.5C302.761 157.737 316.957 168.654 331.198 168.594C345.193 168.241 358.454 156.584 373.039 156.469C383.813 156.469 395.391 162.557 406.469 165.906V134.625C395.39 131.275 383.813 125.187 373.039 125.187C358.454 125.307 345.193 136.929 331.198 137.281C316.957 137.341 302.761 126.425 288.814 126.187C274.671 125.773 261.269 135.868 248.059 135.75C235.452 135.464 224.239 125.357 211.807 125.156V125.156Z"/>
        <path android:fillColor="#00000000"
            android:pathData="M246.406 285.18L351.103 382.096"
            android:strokeColor="#ff8f00" android:strokeLineCap="round" android:strokeWidth="24"/>
        <path android:fillColor="#00000000"
            android:pathData="M451.134 70.6963V251.702H124.451V70.6963"
            android:strokeColor="#ff8f00" android:strokeLineCap="square"
            android:strokeLineJoin="round" android:strokeWidth="30"/>
        <path android:fillColor="#00000000"
            android:pathData="M323.103 285.18L218.406 382.096"
            android:strokeColor="#ff8f00" android:strokeLineCap="round" android:strokeWidth="24"/>
        <path android:fillColor="#00000000"
            android:pathData="M231.517 371.747L402.796 501.304"
            android:strokeColor="#ff8f00" android:strokeLineCap="round" android:strokeWidth="24"/>
        <path android:fillColor="#00000000"
            android:pathData="M340.796 371.747L169.517 501.304"
            android:strokeColor="#ff8f00" android:strokeLineCap="round" android:strokeWidth="24"/>
        <path android:fillColor="#00000000"
            android:pathData="M322.495 253.37C322.495 277.703 358.627 446.193 425.955 531.406"
            android:strokeColor="#ff8f00" android:strokeLineCap="round"
            android:strokeLineJoin="round" android:strokeWidth="30"/>
        <path android:fillColor="#00000000"
            android:pathData="M247.955 253.37C247.955 277.703 211.824 446.193 144.495 531.406"
            android:strokeColor="#ff8f00" android:strokeLineCap="round"
            android:strokeLineJoin="round" android:strokeWidth="30"/>
    </group>
</vector>
