<vector android:height="24dp" android:viewportHeight="580"
    android:viewportWidth="580" android:width="24dp" xmlns:android="http://schemas.android.com/apk/res/android">
    <group>
        <clip-path android:pathData="M0,0H580V580H0V0Z M 0,0"/>
        <path android:fillColor="#00000000"
            android:pathData="M66.2751 1.76863C24.9401 1.76863 1.7041 23.1396 1.7041 66.8046V516.928C1.7041 557.772 22.5991 579.157 63.8961 579.157H515.92C557.227 579.157 578.149 558.842 578.149 516.928V66.8046C578.149 24.2036 557.227 1.76863 514.628 1.76863C514.624 1.76863 66.1331 1.62563 66.2751 1.76863Z"
            android:strokeColor="#EEEEEE" android:strokeWidth="3.408"/>
        <path android:fillColor="#ff8f00" android:fillType="evenOdd" android:pathData="M362.873 153.846L330.154 183.918H390.512L362.873 153.846ZM304.041 207.918L273.096 236.359H438.711L412.57 207.918H304.041ZM246.982 260.359L216.039 288.799H384.393L415.336 260.359H246.982ZM189.928 312.799L187.93 314.635L212.383 341.24H327.334L358.279 312.799H189.928ZM234.439 365.24L265.02 398.512L301.221 365.24H234.439Z"/>
        <path android:fillColor="#ff8f00" android:fillType="evenOdd" android:pathData="M355.767 103.306L526.999 76.4863L487.147 246.253L355.767 103.306Z"/>
        <path android:fillColor="#ff8f00" android:pathData="M418.488 328.195L400.868 309.023L180.389 511.661L198.01 530.833L418.488 328.195Z"/>
        <path android:fillColor="#ff8f00" android:fillType="evenOdd" android:pathData="M138.295 351.157C136.936 351.164 135.595 351.233 134.273 351.36C124.619 352.29 116.245 355.973 109.262 360.315C109.573 360.652 109.904 361.009 110.295 361.456C111.28 362.581 112.311 363.458 113.096 365.405C113.791 367.128 113.989 368.581 114.064 369.362C114.228 371.052 114.044 372.316 114.004 372.618C113.856 373.74 113.623 374.524 113.592 374.635C113.407 375.303 113.25 375.733 113.176 375.938C112.971 376.508 112.78 376.976 112.572 377.491C112.144 378.55 111.591 379.86 110.93 381.411C110.261 382.98 109.327 385.119 108.49 387.051C110.386 386.887 112.376 386.713 114.021 386.577C116.009 384.849 118.198 383.126 120.557 381.563C125.684 378.165 131.277 375.761 136.574 375.251C141.872 374.74 147.028 375.643 153.576 380.346C171.807 393.44 190.894 393.271 203.844 389.151C216.794 385.031 225.148 377.235 225.148 377.235L208.844 359.624C208.844 359.624 204.215 363.849 196.568 366.282C188.922 368.715 179.798 369.63 167.576 360.852C159.473 355.032 150.736 352.031 142.416 351.323C141.029 351.205 139.654 351.15 138.295 351.157Z"/>
        <path android:fillColor="#ff8f00" android:fillType="evenOdd" android:pathData="M118.681 436.854C118.538 437.176 84.614 428.697 84.3688 428.949C84.1231 429.202 93.5216 462.947 93.2047 463.102C92.8883 463.256 72.3509 434.955 72.0006 434.991C71.6497 435.027 57.1588 466.918 56.8165 466.833C56.4747 466.748 58.934 431.867 58.6426 431.669C58.3506 431.471 26.7507 446.586 26.5432 446.301C26.3361 446.016 50.6412 420.877 50.545 420.538C50.4487 420.199 16.5257 411.466 16.5501 411.114C16.5744 410.762 51.3529 407.127 51.4969 406.806C51.6412 406.484 31.2681 377.989 31.513 377.735C31.7575 377.482 60.7359 397.052 61.0528 396.898C61.3702 396.745 64.0798 361.821 64.4306 361.784C64.7808 361.747 74.4 395.365 74.7414 395.451C75.0835 395.538 99.6079 370.526 99.9005 370.723C100.193 370.92 85.9515 402.856 86.1577 403.142C86.3643 403.428 121.228 400.032 121.326 400.371C121.423 400.709 89.9853 416.02 89.9599 416.371C89.9343 416.723 118.825 436.531 118.681 436.854V436.854Z"/>
    </group>
</vector>
